tabxar/__init__.py
tabxar/clean.py
tabxar/r_1.py
tabxar/r_10.py
tabxar/r_100.py
tabxar/r_101.py
tabxar/r_102.py
tabxar/r_103.py
tabxar/r_104.py
tabxar/r_105.py
tabxar/r_106.py
tabxar/r_107.py
tabxar/r_108.py
tabxar/r_109.py
tabxar/r_11.py
tabxar/r_110.py
tabxar/r_111.py
tabxar/r_112.py
tabxar/r_113.py
tabxar/r_114.py
tabxar/r_115.py
tabxar/r_116.py
tabxar/r_117.py
tabxar/r_118.py
tabxar/r_119.py
tabxar/r_12.py
tabxar/r_120.py
tabxar/r_121.py
tabxar/r_122.py
tabxar/r_123.py
tabxar/r_124.py
tabxar/r_125.py
tabxar/r_126.py
tabxar/r_127.py
tabxar/r_128.py
tabxar/r_129.py
tabxar/r_13.py
tabxar/r_130.py
tabxar/r_131.py
tabxar/r_132.py
tabxar/r_133.py
tabxar/r_134.py
tabxar/r_135.py
tabxar/r_136.py
tabxar/r_137.py
tabxar/r_138.py
tabxar/r_139.py
tabxar/r_14.py
tabxar/r_140.py
tabxar/r_141.py
tabxar/r_142.py
tabxar/r_143.py
tabxar/r_144.py
tabxar/r_145.py
tabxar/r_146.py
tabxar/r_147.py
tabxar/r_148.py
tabxar/r_149.py
tabxar/r_15.py
tabxar/r_150.py
tabxar/r_151.py
tabxar/r_152.py
tabxar/r_153.py
tabxar/r_154.py
tabxar/r_155.py
tabxar/r_156.py
tabxar/r_157.py
tabxar/r_158.py
tabxar/r_159.py
tabxar/r_16.py
tabxar/r_160.py
tabxar/r_161.py
tabxar/r_162.py
tabxar/r_163.py
tabxar/r_164.py
tabxar/r_165.py
tabxar/r_166.py
tabxar/r_167.py
tabxar/r_168.py
tabxar/r_169.py
tabxar/r_17.py
tabxar/r_170.py
tabxar/r_171.py
tabxar/r_172.py
tabxar/r_173.py
tabxar/r_174.py
tabxar/r_175.py
tabxar/r_176.py
tabxar/r_177.py
tabxar/r_178.py
tabxar/r_179.py
tabxar/r_18.py
tabxar/r_180.py
tabxar/r_181.py
tabxar/r_182.py
tabxar/r_183.py
tabxar/r_184.py
tabxar/r_185.py
tabxar/r_186.py
tabxar/r_187.py
tabxar/r_188.py
tabxar/r_189.py
tabxar/r_19.py
tabxar/r_190.py
tabxar/r_191.py
tabxar/r_192.py
tabxar/r_193.py
tabxar/r_194.py
tabxar/r_195.py
tabxar/r_196.py
tabxar/r_197.py
tabxar/r_198.py
tabxar/r_199.py
tabxar/r_2.py
tabxar/r_20.py
tabxar/r_200.py
tabxar/r_201.py
tabxar/r_202.py
tabxar/r_203.py
tabxar/r_204.py
tabxar/r_205.py
tabxar/r_206.py
tabxar/r_207.py
tabxar/r_208.py
tabxar/r_209.py
tabxar-0.1.173790171.dist-info/METADATA
tabxar-0.1.173790171.dist-info/WHEEL
tabxar-0.1.173790171.dist-info/top_level.txt
tabxar-0.1.173790171.dist-info/RECORD
